{
    "display": {
        "title": "発展自動採掘機",
        "description": "発展自動採掘機 をクラフトする",
        "icon": {
            "item": "minecraft:command_block"
        },
        "frame": "task",
        "background": "minecraft:textures/block/iron_block.png"
    },
    "criteria": {
        "placeholder": {
            "trigger": "minecraft:recipe_unlocked",
            "conditions": {
                "recipe": "auto-excavator:auto-excavator8"
            }
        }
    },
    "rewards": {
        "function": "auto-excavator:craft/auto-excavator8"
    }
}
